rsyncmanager/__init__.py
rsyncmanager/rsyncmanager.py
rsyncmanager/utils.py
rsyncmanager/version.py
rsyncmanager/test/__init__.py
rsyncmanager/test/test_rsyncmanager.py
rsyncmanager-0.1.4.dist-info/METADATA
rsyncmanager-0.1.4.dist-info/WHEEL
rsyncmanager-0.1.4.dist-info/top_level.txt
rsyncmanager-0.1.4.dist-info/RECORD
