Metadata-Version: 2.2
Name: rsyncmanager
Version: 0.1.4
Summary: API for calling rsync
Home-page: https://gitlab.esrf.fr/payno/rsyncmanager
Author: ESRF
Author-email: henri.paynof@esrf.fr
License: MIT
Project-URL: Source, https://gitlab.esrf.fr/payno/rsyncmanager
Project-URL: Tracker, https://gitlab.esrf.fr/payno/rsyncmanager/issues/
Classifier: Intended Audience :: Science/Research
Classifier: License :: OSI Approved :: MIT License
Classifier: Programming Language :: Python :: 3
Requires-Python: >=3.8
Requires-Dist: silx>=0.9
Requires-Dist: lxml
